README.md
setup.py
drf_client/__init__.py
drf_client/api_node.py
drf_client/client.py
drf_client/rest_result_list.py
drf_client.egg-info/PKG-INFO
drf_client.egg-info/SOURCES.txt
drf_client.egg-info/dependency_links.txt
drf_client.egg-info/not-zip-safe
drf_client.egg-info/requires.txt
drf_client.egg-info/top_level.txt