Metadata-Version: 2.1
Name: drf-client
Version: 1.0.0
Summary: Dynamic rest client for DRF based django api servers
Home-page: https://github.com/sheoran/django-drf-client.git
Author: Deepak Sheoran
License: UNKNOWN
Platform: UNKNOWN
Classifier: Programming Language :: Python
Classifier: Programming Language :: Python :: 3
